addrmatcher/__init__.py
addrmatcher/__main__.py
addrmatcher/hierarchy.py
addrmatcher/matcher.py
addrmatcher/region.py
addrmatcher/resource.py
addrmatcher/hierarchies/AUS.py
addrmatcher/hierarchies/__init__.py
addrmatcher-0.0.2.5.10.dist-info/LICENSE
addrmatcher-0.0.2.5.10.dist-info/METADATA
addrmatcher-0.0.2.5.10.dist-info/WHEEL
addrmatcher-0.0.2.5.10.dist-info/entry_points.txt
addrmatcher-0.0.2.5.10.dist-info/top_level.txt
addrmatcher-0.0.2.5.10.dist-info/RECORD
