Metadata-Version: 2.1
Name: addrmatcher
Version: 0.0.2.5.10
Summary: Australian Address Matcher to Regions
Home-page: https://github.com/uts-mdsi-ilab2-synergy/addrmatcher
Author: Irfan Sampe, Hnin Pwint Tin, Yunseok Oh, Jedo Enriquez
Author-email: addrmatcher@gmail.com
License: UNKNOWN
Project-URL: Source Code, https://github.com/uts-mdsi-ilab2-synergy/addrmatcher
Project-URL: Documentation, https://addrmatcher.readthedocs.io/en/latest/
Project-URL: Bug Tracker, https://github.com/uts-mdsi-ilab2-synergy/addrmatcher/issues
Platform: UNKNOWN
Classifier: Programming Language :: Python :: 3
Classifier: License :: OSI Approved :: MIT License
Classifier: Operating System :: OS Independent
Requires-Python: >=3.6
License-File: LICENSE
Requires-Dist: rapidfuzz
Requires-Dist: scikit-learn (>=0.24.2)
Requires-Dist: pyarrow (>=5.0.0)
Requires-Dist: numpy (>=1.16.6)
Requires-Dist: pandas
Requires-Dist: colorama
Requires-Dist: requests
Requires-Dist: Pillow
